<?xml version="1.0" encoding="UTF-8"?>
<fichero>
<marca>
<AW>Abarth</AW>
<modelo>
<AX>Grande Punto</AX>
<AA>
<AZ>
<Motorizacion>1.4 T 155cv / 116kw 6 marchas</Motorizacion>
<kw>115.5835</kw>
<combustible>G</combustible>
<cv>155</cv>
<cilindrada>1368</cilindrada>
<pesoVacio>1250</pesoVacio>
<Par>230</Par>
<marchas>6</marchas>
<cambio>M</cambio>
<segunda>13.0545087719298</segunda>
<tercera>19.1171111507583</tercera>
<cuarta>26.3530270536153</cuarta>
<quinta>32.0428851674641</quinta>
<sexta>37.8493140233133</sexta>
<septima></septima>
<octava></octava>
<Puertas>3</Puertas>
<Cilindros>4</Cilindros>
<vMAX>208</vMAX>
<aceleracion>8.2</aceleracion>
<Cons1></Cons1>
<Cons2>7.5</Cons2>
<Cons3></Cons3>
<EmisionesCo2>174</EmisionesCo2>
<anioComienzo>2008</anioComienzo>
<anioFin>2010</anioFin>
</AZ>
<AZ>
<Motorizacion>1.4 T 180cv / 134kw 6 marchas</Motorizacion>
<kw>134.226</kw>
<combustible>G</combustible>
<cv>180</cv>
<cilindrada>1368</cilindrada>
<pesoVacio>1250</pesoVacio>
<Par>272</Par>
<marchas>6</marchas>
<cambio>M</cambio>
<segunda>13.1359298245614</segunda>
<tercera>19.2363446922391</tercera>
<cuarta>26.5173910477127</cuarta>
<quinta>32.2427368421053</quinta>
<sexta>38.0853804309431</sexta>
<septima></septima>
<octava></octava>
<Puertas>3</Puertas>
<Cilindros>4</Cilindros>
<vMAX>215</vMAX>
<aceleracion>7.7</aceleracion>
<Cons1></Cons1>
<Cons2>8</Cons2>
<Cons3></Cons3>
<EmisionesCo2>185.6</EmisionesCo2>
<anioComienzo>2008</anioComienzo>
<anioFin>2010</anioFin>
</AZ>
</AA></modelo>
</marca>
</fichero>
