<?xml version="1.0" encoding="UTF-8"?>
<fichero>
<marca>
<AW>Smart</AW>
<modelo>
<AX>Forfour</AX>
<AA>
<AZ>
<Motorizacion>1.1 64cv / 48kw</Motorizacion>
<kw>47.7248</kw>
<combustible>G</combustible>
<cv>64</cv>
<cilindrada>1124</cilindrada>
<pesoVacio>965</pesoVacio>
<Par>92</Par>
<marchas>5</marchas>
<cambio>M</cambio>
<segunda>13.2288641270988</segunda>
<tercera>20.0532781609195</tercera>
<cuarta>26.8799260454879</cuarta>
<quinta>33.2462243194192</quinta>
<sexta></sexta>
<septima></septima>
<octava></octava>
<Puertas>4</Puertas>
<Cilindros>3</Cilindros>
<vMAX>165</vMAX>
<aceleracion>13.5</aceleracion>
<Cons1>4.6</Cons1>
<Cons2>5.5</Cons2>
<Cons3>7</Cons3>
<EmisionesCo2>127.6</EmisionesCo2>
<anioComienzo>2004</anioComienzo>
<anioFin>2006</anioFin>
</AZ>
<AZ>
<Motorizacion>1.1 64cv / 48kw Aut.</Motorizacion>
<kw>47.7248</kw>
<combustible>G</combustible>
<cv>64</cv>
<cilindrada>1124</cilindrada>
<pesoVacio>965</pesoVacio>
<Par>92</Par>
<marchas>6</marchas>
<cambio>A</cambio>
<segunda>12.7032138968829</segunda>
<tercera>19.2564591611479</tercera>
<cuarta>25.8118495138791</cuarta>
<quinta>31.9251822934821</quinta>
<sexta>37.9111539735099</sexta>
<septima></septima>
<octava></octava>
<Puertas>5</Puertas>
<Cilindros>3</Cilindros>
<vMAX>165</vMAX>
<aceleracion>13.5</aceleracion>
<Cons1>4.4</Cons1>
<Cons2>5.3</Cons2>
<Cons3>6.8</Cons3>
<EmisionesCo2>122.96</EmisionesCo2>
<anioComienzo>2004</anioComienzo>
<anioFin>2006</anioFin>
</AZ>
<AZ>
<Motorizacion>1.1 75cv / 56kw</Motorizacion>
<kw>55.9275</kw>
<combustible>G</combustible>
<cv>75</cv>
<cilindrada>1124</cilindrada>
<pesoVacio>965</pesoVacio>
<Par>100</Par>
<marchas>5</marchas>
<cambio>M</cambio>
<segunda>13.2288641270988</segunda>
<tercera>20.0532781609195</tercera>
<cuarta>26.8799260454879</cuarta>
<quinta>33.2462243194192</quinta>
<sexta></sexta>
<septima></septima>
<octava></octava>
<Puertas>5</Puertas>
<Cilindros>3</Cilindros>
<vMAX>165</vMAX>
<aceleracion>13.5</aceleracion>
<Cons1>4.6</Cons1>
<Cons2>5.5</Cons2>
<Cons3>7</Cons3>
<EmisionesCo2>127.6</EmisionesCo2>
<anioComienzo>2004</anioComienzo>
<anioFin>2006</anioFin>
</AZ>
<AZ>
<Motorizacion>1.1 75cv / 56kw Aut.</Motorizacion>
<kw>55.9275</kw>
<combustible>G</combustible>
<cv>75</cv>
<cilindrada>1124</cilindrada>
<pesoVacio>965</pesoVacio>
<Par>100</Par>
<marchas>6</marchas>
<cambio>A</cambio>
<segunda>12.7032138968829</segunda>
<tercera>19.2564591611479</tercera>
<cuarta>25.8118495138791</cuarta>
<quinta>31.9251822934821</quinta>
<sexta>37.9111539735099</sexta>
<septima></septima>
<octava></octava>
<Puertas>5</Puertas>
<Cilindros>3</Cilindros>
<vMAX>165</vMAX>
<aceleracion>13.5</aceleracion>
<Cons1>4.4</Cons1>
<Cons2>5.3</Cons2>
<Cons3>6.8</Cons3>
<EmisionesCo2>122.96</EmisionesCo2>
<anioComienzo>2004</anioComienzo>
<anioFin>2006</anioFin>
</AZ>
<AZ>
<Motorizacion>1.3 95cv / 71kw</Motorizacion>
<kw>70.8415</kw>
<combustible>G</combustible>
<cv>95</cv>
<cilindrada>1332</cilindrada>
<pesoVacio>970</pesoVacio>
<Par>125</Par>
<marchas>5</marchas>
<cambio>M</cambio>
<segunda>13.8330670559807</segunda>
<tercera>20.9691730769231</tercera>
<cuarta>28.1076149754501</cuarta>
<quinta>34.7646816801619</quinta>
<sexta></sexta>
<septima></septima>
<octava></octava>
<Puertas>4</Puertas>
<Cilindros>4</Cilindros>
<vMAX>180</vMAX>
<aceleracion>11</aceleracion>
<Cons1>4.8</Cons1>
<Cons2>5.8</Cons2>
<Cons3>7.4</Cons3>
<EmisionesCo2>134.56</EmisionesCo2>
<anioComienzo>2004</anioComienzo>
<anioFin>2006</anioFin>
</AZ>
<AZ>
<Motorizacion>1.3 95cv / 71kw Aut.</Motorizacion>
<kw>70.8415</kw>
<combustible>G</combustible>
<cv>95</cv>
<cilindrada>1332</cilindrada>
<pesoVacio>970</pesoVacio>
<Par>125</Par>
<marchas>6</marchas>
<cambio>A</cambio>
<segunda>12.7032138968829</segunda>
<tercera>19.2564591611479</tercera>
<cuarta>25.8118495138791</cuarta>
<quinta>31.9251822934821</quinta>
<sexta>37.9111539735099</sexta>
<septima></septima>
<octava></octava>
<Puertas>4</Puertas>
<Cilindros>4</Cilindros>
<vMAX>180</vMAX>
<aceleracion>11</aceleracion>
<Cons1>4.6</Cons1>
<Cons2>5.6</Cons2>
<Cons3>7.3</Cons3>
<EmisionesCo2>129.92</EmisionesCo2>
<anioComienzo>2004</anioComienzo>
<anioFin>2006</anioFin>
</AZ>
<AZ>
<Motorizacion>1.5 109cv / 81kw</Motorizacion>
<kw>81.2813</kw>
<combustible>G</combustible>
<cv>109</cv>
<cilindrada>1499</cilindrada>
<pesoVacio>975</pesoVacio>
<Par>145</Par>
<marchas>5</marchas>
<cambio>M</cambio>
<segunda>13.6646314941603</segunda>
<tercera>20.7138461538462</tercera>
<cuarta>27.7653682487725</cuarta>
<quinta>34.3413765182186</quinta>
<sexta></sexta>
<septima></septima>
<octava></octava>
<Puertas>4</Puertas>
<Cilindros>4</Cilindros>
<vMAX>190</vMAX>
<aceleracion>9.8</aceleracion>
<Cons1>4.9</Cons1>
<Cons2>5.9</Cons2>
<Cons3>7.6</Cons3>
<EmisionesCo2>136.88</EmisionesCo2>
<anioComienzo>2004</anioComienzo>
<anioFin>2006</anioFin>
</AZ>
<AZ>
<Motorizacion>1.5 109cv / 81kw Aut.</Motorizacion>
<kw>81.2813</kw>
<combustible>G</combustible>
<cv>109</cv>
<cilindrada>1499</cilindrada>
<pesoVacio>975</pesoVacio>
<Par>145</Par>
<marchas>6</marchas>
<cambio>A</cambio>
<segunda>12.5485357650567</segunda>
<tercera>19.0219867549669</tercera>
<cuarta>25.4975567141046</cuarta>
<quinta>31.5364517253398</quinta>
<sexta>37.4495364238411</sexta>
<septima></septima>
<octava></octava>
<Puertas>4</Puertas>
<Cilindros>4</Cilindros>
<vMAX>190</vMAX>
<aceleracion>9.8</aceleracion>
<Cons1>5.1</Cons1>
<Cons2>6.2</Cons2>
<Cons3>8</Cons3>
<EmisionesCo2>143.84</EmisionesCo2>
<anioComienzo>2004</anioComienzo>
<anioFin>2006</anioFin>
</AZ>
<AZ>
<Motorizacion>1.5 177cv / 132kw Brabus</Motorizacion>
<kw>131.9889</kw>
<combustible>G</combustible>
<cv>177</cv>
<cilindrada>1468</cilindrada>
<pesoVacio>1090</pesoVacio>
<Par>230</Par>
<marchas>5</marchas>
<cambio>M</cambio>
<segunda>14.1</segunda>
<tercera>21.5</tercera>
<cuarta>28.1</cuarta>
<quinta>34.6</quinta>
<sexta></sexta>
<septima></septima>
<octava></octava>
<Puertas>4</Puertas>
<Cilindros>4</Cilindros>
<vMAX>221</vMAX>
<aceleracion>6.9</aceleracion>
<Cons1>5.6</Cons1>
<Cons2>6.8</Cons2>
<Cons3>8.9</Cons3>
<EmisionesCo2>157.76</EmisionesCo2>
<anioComienzo>2004</anioComienzo>
<anioFin>2006</anioFin>
</AZ>
<AZ>
<Motorizacion>1.5 TDCi 68cv / 51kw</Motorizacion>
<kw>50.7076</kw>
<combustible>D</combustible>
<cv>68</cv>
<cilindrada>1332</cilindrada>
<pesoVacio>970</pesoVacio>
<Par>125</Par>
<marchas>5</marchas>
<cambio>M</cambio>
<segunda>15.1991623036649</segunda>
<tercera>23.7954098360656</tercera>
<cuarta>34.1534117647059</cuarta>
<quinta>44.6621538461538</quinta>
<sexta></sexta>
<septima></septima>
<octava></octava>
<Puertas>4</Puertas>
<Cilindros>4</Cilindros>
<vMAX>160</vMAX>
<aceleracion>13.9</aceleracion>
<Cons1>3.9</Cons1>
<Cons2>4.6</Cons2>
<Cons3>5.9</Cons3>
<EmisionesCo2>121.9</EmisionesCo2>
<anioComienzo>2004</anioComienzo>
<anioFin>2006</anioFin>
</AZ>
<AZ>
<Motorizacion>1.5 TDCi 68cv / 51kw Aut.</Motorizacion>
<kw>50.7076</kw>
<combustible>D</combustible>
<cv>68</cv>
<cilindrada>1332</cilindrada>
<pesoVacio>970</pesoVacio>
<Par>125</Par>
<marchas>6</marchas>
<cambio>A</cambio>
<segunda>15.1991623036649</segunda>
<tercera>23.7954098360656</tercera>
<cuarta>34.1534117647059</cuarta>
<quinta>44.6621538461538</quinta>
<sexta>53.76</sexta>
<septima></septima>
<octava></octava>
<Puertas>4</Puertas>
<Cilindros>4</Cilindros>
<vMAX>160</vMAX>
<aceleracion>13.9</aceleracion>
<Cons1>3.9</Cons1>
<Cons2>4.6</Cons2>
<Cons3>5.9</Cons3>
<EmisionesCo2>121.9</EmisionesCo2>
<anioComienzo>2004</anioComienzo>
<anioFin>2006</anioFin>
</AZ>
<AZ>
<Motorizacion>1.5 TDCi 95cv / 71kw</Motorizacion>
<kw>70.8415</kw>
<combustible>D</combustible>
<cv>95</cv>
<cilindrada>1332</cilindrada>
<pesoVacio>970</pesoVacio>
<Par>125</Par>
<marchas>5</marchas>
<cambio>M</cambio>
<segunda>15.1991623036649</segunda>
<tercera>23.7954098360656</tercera>
<cuarta>34.1534117647059</cuarta>
<quinta>44.6621538461538</quinta>
<sexta></sexta>
<septima></septima>
<octava></octava>
<Puertas>4</Puertas>
<Cilindros>4</Cilindros>
<vMAX>180</vMAX>
<aceleracion>10.5</aceleracion>
<Cons1>3.8</Cons1>
<Cons2>4.4</Cons2>
<Cons3>5.5</Cons3>
<EmisionesCo2>116.6</EmisionesCo2>
<anioComienzo>2004</anioComienzo>
<anioFin>2006</anioFin>
</AZ>
<AZ>
<Motorizacion>1.5 TDCi 95cv / 71kw Aut.</Motorizacion>
<kw>70.8415</kw>
<combustible>D</combustible>
<cv>95</cv>
<cilindrada>1332</cilindrada>
<pesoVacio>970</pesoVacio>
<Par>125</Par>
<marchas>6</marchas>
<cambio>A</cambio>
<segunda>15.1991623036649</segunda>
<tercera>23.7954098360656</tercera>
<cuarta>34.1534117647059</cuarta>
<quinta>44.6621538461538</quinta>
<sexta>53.76</sexta>
<septima></septima>
<octava></octava>
<Puertas>4</Puertas>
<Cilindros>4</Cilindros>
<vMAX>180</vMAX>
<aceleracion>10.5</aceleracion>
<Cons1>3.8</Cons1>
<Cons2>4.4</Cons2>
<Cons3>5.5</Cons3>
<EmisionesCo2>116.6</EmisionesCo2>
<anioComienzo>2004</anioComienzo>
<anioFin>2006</anioFin>
</AZ>
</AA></modelo>
<modelo>
<AX>Fortwo</AX>
<AA>
<AZ>
<Motorizacion>1.0 71cv / 53kw Aut.</Motorizacion>
<kw>52.9447</kw>
<combustible>G</combustible>
<cv>71</cv>
<cilindrada>999</cilindrada>
<pesoVacio>750</pesoVacio>
<Par>92</Par>
<marchas>5</marchas>
<cambio>A</cambio>
<segunda>12.3524648937277</segunda>
<tercera>18.7247682119205</tercera>
<cuarta>25.0991573904467</cuarta>
<quinta>30.6405298013245</quinta>
<sexta></sexta>
<septima></septima>
<octava></octava>
<Puertas>2</Puertas>
<Cilindros>3</Cilindros>
<vMAX>145</vMAX>
<aceleracion>13.3</aceleracion>
<Cons1>4</Cons1>
<Cons2>4.7</Cons2>
<Cons3>6.1</Cons3>
<EmisionesCo2>112</EmisionesCo2>
<anioComienzo>2007</anioComienzo>
<anioFin>2010</anioFin>
</AZ>
<AZ>
<Motorizacion>1.0 71cv / 53kw Aut. Cabrio</Motorizacion>
<kw>52.9447</kw>
<combustible>G</combustible>
<cv>71</cv>
<cilindrada>999</cilindrada>
<pesoVacio>790</pesoVacio>
<Par>92</Par>
<marchas>5</marchas>
<cambio>A</cambio>
<segunda>12.3524648937277</segunda>
<tercera>18.7247682119205</tercera>
<cuarta>25.0991573904467</cuarta>
<quinta>30.6405298013245</quinta>
<sexta></sexta>
<septima></septima>
<octava></octava>
<Puertas>2</Puertas>
<Cilindros>3</Cilindros>
<vMAX>145</vMAX>
<aceleracion>13.3</aceleracion>
<Cons1>4.1</Cons1>
<Cons2>4.9</Cons2>
<Cons3>6.6</Cons3>
<EmisionesCo2>116</EmisionesCo2>
<anioComienzo>2007</anioComienzo>
<anioFin>2010</anioFin>
</AZ>
<AZ>
<Motorizacion>1.0 71cv / 53kw Aut. MHD</Motorizacion>
<kw>52.9447</kw>
<combustible>G</combustible>
<cv>71</cv>
<cilindrada>999</cilindrada>
<pesoVacio>750</pesoVacio>
<Par>92</Par>
<marchas>5</marchas>
<cambio>A</cambio>
<segunda>12.3524648937277</segunda>
<tercera>18.7247682119205</tercera>
<cuarta>25.0991573904467</cuarta>
<quinta>30.6405298013245</quinta>
<sexta></sexta>
<septima></septima>
<octava></octava>
<Puertas>2</Puertas>
<Cilindros>3</Cilindros>
<vMAX>145</vMAX>
<aceleracion>13.3</aceleracion>
<Cons1>3.9</Cons1>
<Cons2>4.3</Cons2>
<Cons3>4.9</Cons3>
<EmisionesCo2>103</EmisionesCo2>
<anioComienzo>2009</anioComienzo>
<anioFin>2010</anioFin>
</AZ>
<AZ>
<Motorizacion>1.0 T 84cv / 63kw Aut.</Motorizacion>
<kw>62.6388</kw>
<combustible>G</combustible>
<cv>84</cv>
<cilindrada>999</cilindrada>
<pesoVacio>780</pesoVacio>
<Par>120</Par>
<marchas>5</marchas>
<cambio>A</cambio>
<segunda>12.494071634132</segunda>
<tercera>18.9394260485651</tercera>
<cuarta>25.3868902353107</cuarta>
<quinta>33.6108124242142</quinta>
<sexta></sexta>
<septima></septima>
<octava></octava>
<Puertas>2</Puertas>
<Cilindros>3</Cilindros>
<vMAX>145</vMAX>
<aceleracion>10.9</aceleracion>
<Cons1>4.1</Cons1>
<Cons2>4.9</Cons2>
<Cons3>6.4</Cons3>
<EmisionesCo2>116</EmisionesCo2>
<anioComienzo>2007</anioComienzo>
<anioFin>2010</anioFin>
</AZ>
<AZ>
<Motorizacion>1.0 T 84cv / 63kw Aut. Cabrio</Motorizacion>
<kw>62.6388</kw>
<combustible>G</combustible>
<cv>84</cv>
<cilindrada>999</cilindrada>
<pesoVacio>820</pesoVacio>
<Par>120</Par>
<marchas>5</marchas>
<cambio>A</cambio>
<segunda>12.494071634132</segunda>
<tercera>18.9394260485651</tercera>
<cuarta>25.3868902353107</cuarta>
<quinta>33.6108124242142</quinta>
<sexta></sexta>
<septima></septima>
<octava></octava>
<Puertas>2</Puertas>
<Cilindros>3</Cilindros>
<vMAX>145</vMAX>
<aceleracion>10.9</aceleracion>
<Cons1>4.1</Cons1>
<Cons2>4.9</Cons2>
<Cons3>6.4</Cons3>
<EmisionesCo2>116</EmisionesCo2>
<anioComienzo>2007</anioComienzo>
<anioFin>2010</anioFin>
</AZ>
<AZ>
<Motorizacion>1.0 T Brabus 98cv / 73kw Aut.</Motorizacion>
<kw>73.0786</kw>
<combustible>G</combustible>
<cv>98</cv>
<cilindrada>999</cilindrada>
<pesoVacio>780</pesoVacio>
<Par>140</Par>
<marchas>5</marchas>
<cambio>A</cambio>
<segunda>14.1911739537464</segunda>
<tercera>21.5120176600441</tercera>
<cuarta>28.8352577145273</cuarta>
<quinta>38.1762566924727</quinta>
<sexta></sexta>
<septima></septima>
<octava></octava>
<Puertas>2</Puertas>
<Cilindros>3</Cilindros>
<vMAX>155</vMAX>
<aceleracion>9.9</aceleracion>
<Cons1>4.4</Cons1>
<Cons2>5.2</Cons2>
<Cons3>6.5</Cons3>
<EmisionesCo2>124</EmisionesCo2>
<anioComienzo>2008</anioComienzo>
<anioFin>2010</anioFin>
</AZ>
<AZ>
<Motorizacion>1.0 T Brabus 98cv / 73kw Aut. Cabrio</Motorizacion>
<kw>73.0786</kw>
<combustible>G</combustible>
<cv>98</cv>
<cilindrada>999</cilindrada>
<pesoVacio>810</pesoVacio>
<Par>140</Par>
<marchas>5</marchas>
<cambio>A</cambio>
<segunda>14.1911739537464</segunda>
<tercera>21.5120176600441</tercera>
<cuarta>28.8352577145273</cuarta>
<quinta>38.1762566924727</quinta>
<sexta></sexta>
<septima></septima>
<octava></octava>
<Puertas>2</Puertas>
<Cilindros>3</Cilindros>
<vMAX>155</vMAX>
<aceleracion>9.9</aceleracion>
<Cons1>4.4</Cons1>
<Cons2>5.2</Cons2>
<Cons3>6.5</Cons3>
<EmisionesCo2>124</EmisionesCo2>
<anioComienzo>2008</anioComienzo>
<anioFin>2010</anioFin>
</AZ>
<AZ>
<Motorizacion>0.6 45cv / 34kw</Motorizacion>
<kw>33.5565</kw>
<combustible>G</combustible>
<cv>45</cv>
<cilindrada>599</cilindrada>
<pesoVacio>720</pesoVacio>
<Par>70</Par>
<marchas>6</marchas>
<cambio>M</cambio>
<segunda>10.2</segunda>
<tercera>14.2</tercera>
<cuarta>18.7</cuarta>
<quinta>25.7</quinta>
<sexta>35.8</sexta>
<septima></septima>
<octava></octava>
<Puertas>2</Puertas>
<Cilindros>3</Cilindros>
<vMAX>135</vMAX>
<aceleracion>18.9</aceleracion>
<Cons1>4.3</Cons1>
<Cons2>4.9</Cons2>
<Cons3>6.1</Cons3>
<EmisionesCo2>113.68</EmisionesCo2>
<anioComienzo>1999</anioComienzo>
<anioFin>2002</anioFin>
</AZ>
<AZ>
<Motorizacion>0.6 54cv / 40kw</Motorizacion>
<kw>40.2678</kw>
<combustible>G</combustible>
<cv>54</cv>
<cilindrada>599</cilindrada>
<pesoVacio>720</pesoVacio>
<Par>80</Par>
<marchas>6</marchas>
<cambio>M</cambio>
<segunda>10.2</segunda>
<tercera>14.2</tercera>
<cuarta>18.7</cuarta>
<quinta>25.7</quinta>
<sexta>35.8</sexta>
<septima></septima>
<octava></octava>
<Puertas>2</Puertas>
<Cilindros>3</Cilindros>
<vMAX>135</vMAX>
<aceleracion>17.2</aceleracion>
<Cons1>4.8</Cons1>
<Cons2>5.9</Cons2>
<Cons3>7</Cons3>
<EmisionesCo2>136.88</EmisionesCo2>
<anioComienzo>1999</anioComienzo>
<anioFin>2002</anioFin>
</AZ>
<AZ>
<Motorizacion>0.6 54cv / 40kw Aut.</Motorizacion>
<kw>40.2678</kw>
<combustible>G</combustible>
<cv>54</cv>
<cilindrada>599</cilindrada>
<pesoVacio>720</pesoVacio>
<Par>80</Par>
<marchas>6</marchas>
<cambio>A</cambio>
<segunda>10.2</segunda>
<tercera>14.2</tercera>
<cuarta>18.7</cuarta>
<quinta>25.7</quinta>
<sexta>35.8</sexta>
<septima></septima>
<octava></octava>
<Puertas>2</Puertas>
<Cilindros>3</Cilindros>
<vMAX>135</vMAX>
<aceleracion>17.2</aceleracion>
<Cons1>4.8</Cons1>
<Cons2>5.9</Cons2>
<Cons3>7</Cons3>
<EmisionesCo2>136.88</EmisionesCo2>
<anioComienzo>1999</anioComienzo>
<anioFin>2002</anioFin>
</AZ>
<AZ>
<Motorizacion>0.6 61cv / 45kw</Motorizacion>
<kw>45.4877</kw>
<combustible>G</combustible>
<cv>61</cv>
<cilindrada>599</cilindrada>
<pesoVacio>720</pesoVacio>
<Par>88</Par>
<marchas>6</marchas>
<cambio>M</cambio>
<segunda>10.2</segunda>
<tercera>14.2</tercera>
<cuarta>18.7</cuarta>
<quinta>25.7</quinta>
<sexta>35.8</sexta>
<septima></septima>
<octava></octava>
<Puertas>2</Puertas>
<Cilindros>3</Cilindros>
<vMAX>135</vMAX>
<aceleracion>16.8</aceleracion>
<Cons1>4.3</Cons1>
<Cons2>4.9</Cons2>
<Cons3>6.1</Cons3>
<EmisionesCo2>113.68</EmisionesCo2>
<anioComienzo>2001</anioComienzo>
<anioFin>2002</anioFin>
</AZ>
<AZ>
<Motorizacion>0.6 70cv / 52kw</Motorizacion>
<kw>52.199</kw>
<combustible>G</combustible>
<cv>70</cv>
<cilindrada>599</cilindrada>
<pesoVacio>730</pesoVacio>
<Par>100</Par>
<marchas>6</marchas>
<cambio>M</cambio>
<segunda>11.1774752186589</segunda>
<tercera>15.5595535714286</tercera>
<cuarta>20.4902599732773</cuarta>
<quinta>28.2681953917051</quinta>
<sexta>39.3506129032258</sexta>
<septima></septima>
<octava></octava>
<Puertas>2</Puertas>
<Cilindros>3</Cilindros>
<vMAX></vMAX>
<aceleracion>17</aceleracion>
<Cons1>4.9</Cons1>
<Cons2>5.4</Cons2>
<Cons3>6.4</Cons3>
<EmisionesCo2>125.28</EmisionesCo2>
<anioComienzo>2003</anioComienzo>
<anioFin>2004</anioFin>
</AZ>
<AZ>
<Motorizacion>0.7 50cv / 37kw</Motorizacion>
<kw>37.285</kw>
<combustible>G</combustible>
<cv>50</cv>
<cilindrada>698</cilindrada>
<pesoVacio>730</pesoVacio>
<Par>80</Par>
<marchas>6</marchas>
<cambio>M</cambio>
<segunda>11.1774752186589</segunda>
<tercera>15.5595535714286</tercera>
<cuarta>20.4902599732773</cuarta>
<quinta>28.2681953917051</quinta>
<sexta>39.3506129032258</sexta>
<septima></septima>
<octava></octava>
<Puertas>2</Puertas>
<Cilindros>3</Cilindros>
<vMAX>135</vMAX>
<aceleracion>18.3</aceleracion>
<Cons1>4</Cons1>
<Cons2>4.7</Cons2>
<Cons3>6</Cons3>
<EmisionesCo2>109.04</EmisionesCo2>
<anioComienzo>2003</anioComienzo>
<anioFin>2006</anioFin>
</AZ>
<AZ>
<Motorizacion>0.7 61cv / 45kw</Motorizacion>
<kw>45.4877</kw>
<combustible>G</combustible>
<cv>61</cv>
<cilindrada>698</cilindrada>
<pesoVacio>730</pesoVacio>
<Par>95</Par>
<marchas>6</marchas>
<cambio>M</cambio>
<segunda>11.1774752186589</segunda>
<tercera>15.5595535714286</tercera>
<cuarta>20.4902599732773</cuarta>
<quinta>28.2681953917051</quinta>
<sexta>39.3506129032258</sexta>
<septima></septima>
<octava></octava>
<Puertas>2</Puertas>
<Cilindros>3</Cilindros>
<vMAX>135</vMAX>
<aceleracion>15.5</aceleracion>
<Cons1></Cons1>
<Cons2></Cons2>
<Cons3></Cons3>
<EmisionesCo2>0</EmisionesCo2>
<anioComienzo>2003</anioComienzo>
<anioFin>2006</anioFin>
</AZ>
<AZ>
<Motorizacion>0.7 75cv / 56kw Aut. Brabus</Motorizacion>
<kw>55.9275</kw>
<combustible>G</combustible>
<cv>75</cv>
<cilindrada>698</cilindrada>
<pesoVacio>730</pesoVacio>
<Par>110</Par>
<marchas>6</marchas>
<cambio>A</cambio>
<segunda>11.3</segunda>
<tercera>14.7</tercera>
<cuarta>18.7</cuarta>
<quinta>25.7</quinta>
<sexta>33.6</sexta>
<septima></septima>
<octava></octava>
<Puertas>2</Puertas>
<Cilindros>3</Cilindros>
<vMAX>150</vMAX>
<aceleracion>12.3</aceleracion>
<Cons1>4.6</Cons1>
<Cons2>5.5</Cons2>
<Cons3>6.4</Cons3>
<EmisionesCo2>127.6</EmisionesCo2>
<anioComienzo>2004</anioComienzo>
<anioFin>2006</anioFin>
</AZ>
<AZ>
<Motorizacion>0.8 CDi 45cv / 34kw Aut.</Motorizacion>
<kw>33.5565</kw>
<combustible>D</combustible>
<cv>45</cv>
<cilindrada>799</cilindrada>
<pesoVacio>780</pesoVacio>
<Par>110</Par>
<marchas>5</marchas>
<cambio>A</cambio>
<segunda>12.3524648937277</segunda>
<tercera>18.7247682119205</tercera>
<cuarta>26.5092224123819</cuarta>
<quinta>36.2972429954152</quinta>
<sexta></sexta>
<septima></septima>
<octava></octava>
<Puertas>2</Puertas>
<Cilindros>3</Cilindros>
<vMAX>145</vMAX>
<aceleracion>16.7</aceleracion>
<Cons1>3.2</Cons1>
<Cons2>3.3</Cons2>
<Cons3>3.4</Cons3>
<EmisionesCo2>88</EmisionesCo2>
<anioComienzo>2007</anioComienzo>
<anioFin>2008</anioFin>
</AZ>
<AZ>
<Motorizacion>0.8 CDi 45cv / 34kw Aut. Cabrio</Motorizacion>
<kw>33.5565</kw>
<combustible>D</combustible>
<cv>45</cv>
<cilindrada>799</cilindrada>
<pesoVacio>820</pesoVacio>
<Par>110</Par>
<marchas>5</marchas>
<cambio>A</cambio>
<segunda>12.3524648937277</segunda>
<tercera>18.7247682119205</tercera>
<cuarta>26.5092224123819</cuarta>
<quinta>36.2972429954152</quinta>
<sexta></sexta>
<septima></septima>
<octava></octava>
<Puertas>2</Puertas>
<Cilindros>3</Cilindros>
<vMAX>145</vMAX>
<aceleracion>16.7</aceleracion>
<Cons1>3.2</Cons1>
<Cons2>3.3</Cons2>
<Cons3>3.4</Cons3>
<EmisionesCo2>88</EmisionesCo2>
<anioComienzo>2007</anioComienzo>
<anioFin>2008</anioFin>
</AZ>
<AZ>
<Motorizacion>0.8 CDi 54cv / 40kw Aut.</Motorizacion>
<kw>40</kw>
<combustible>D</combustible>
<cv>54</cv>
<cilindrada>799</cilindrada>
<pesoVacio>780</pesoVacio>
<Par>130</Par>
<marchas>5</marchas>
<cambio>A</cambio>
<segunda>12.3524648937277</segunda>
<tercera>18.7247682119205</tercera>
<cuarta>26.5092224123819</cuarta>
<quinta>36.2972429954152</quinta>
<sexta></sexta>
<septima></septima>
<octava></octava>
<Puertas>2</Puertas>
<Cilindros>3</Cilindros>
<vMAX>145</vMAX>
<aceleracion>16.8</aceleracion>
<Cons1>3.4</Cons1>
<Cons2>3.4</Cons2>
<Cons3>3.4</Cons3>
<EmisionesCo2>88</EmisionesCo2>
<anioComienzo>2009</anioComienzo>
<anioFin>2010</anioFin>
</AZ>
<AZ>
<Motorizacion>0.8 TDCi 41cv / 31kw Aut.</Motorizacion>
<kw>30.5737</kw>
<combustible>D</combustible>
<cv>41</cv>
<cilindrada>799</cilindrada>
<pesoVacio>730</pesoVacio>
<Par>100</Par>
<marchas>6</marchas>
<cambio>A</cambio>
<segunda>11.9388836123005</segunda>
<tercera>16.6194686648501</tercera>
<cuarta>23.5258540433925</cuarta>
<quinta>32.4560761904762</quinta>
<sexta>45.1803333333333</sexta>
<septima></septima>
<octava></octava>
<Puertas>2</Puertas>
<Cilindros>3</Cilindros>
<vMAX>135</vMAX>
<aceleracion>19.8</aceleracion>
<Cons1>3.1</Cons1>
<Cons2>3.4</Cons2>
<Cons3>3.9</Cons3>
<EmisionesCo2>90.1</EmisionesCo2>
<anioComienzo>1999</anioComienzo>
<anioFin>2006</anioFin>
</AZ>
<AZ>
<Motorizacion>1.0 61cv / 45kw Aut.</Motorizacion>
<kw>45.4877</kw>
<combustible>G</combustible>
<cv>61</cv>
<cilindrada>999</cilindrada>
<pesoVacio>750</pesoVacio>
<Par>89</Par>
<marchas>5</marchas>
<cambio>A</cambio>
<segunda>12.3524648937277</segunda>
<tercera>18.7247682119205</tercera>
<cuarta>25.0991573904467</cuarta>
<quinta>30.6405298013245</quinta>
<sexta></sexta>
<septima></septima>
<octava></octava>
<Puertas>2</Puertas>
<Cilindros>3</Cilindros>
<vMAX>145</vMAX>
<aceleracion>16.7</aceleracion>
<Cons1>4</Cons1>
<Cons2>4.7</Cons2>
<Cons3>6.1</Cons3>
<EmisionesCo2>112</EmisionesCo2>
<anioComienzo>2007</anioComienzo>
<anioFin>2010</anioFin>
</AZ>
</AA></modelo>
<modelo>
<AX>Roadster</AX>
<AA>
<AZ>
<Motorizacion>0.7 101cv / 75kw Brabus</Motorizacion>
<kw>75.3157</kw>
<combustible>G</combustible>
<cv>101</cv>
<cilindrada>698</cilindrada>
<pesoVacio>740</pesoVacio>
<Par>130</Par>
<marchas>6</marchas>
<cambio>M</cambio>
<segunda>11.4718775510204</segunda>
<tercera>14.9500531914894</tercera>
<cuarta>18.9514091096739</cuarta>
<quinta>26.1452093023256</quinta>
<sexta>34.0722142503711</sexta>
<septima></septima>
<octava></octava>
<Puertas>2</Puertas>
<Cilindros>3</Cilindros>
<vMAX>195</vMAX>
<aceleracion>9.8</aceleracion>
<Cons1>4.6</Cons1>
<Cons2>5.3</Cons2>
<Cons3>6.6</Cons3>
<EmisionesCo2>122.96</EmisionesCo2>
<anioComienzo>2003</anioComienzo>
<anioFin>2006</anioFin>
</AZ>
<AZ>
<Motorizacion>0.7 101cv / 75kw Brabus Aut.</Motorizacion>
<kw>75.3157</kw>
<combustible>G</combustible>
<cv>101</cv>
<cilindrada>698</cilindrada>
<pesoVacio>740</pesoVacio>
<Par>130</Par>
<marchas>6</marchas>
<cambio>A</cambio>
<segunda>11.4718775510204</segunda>
<tercera>14.9500531914894</tercera>
<cuarta>18.9514091096739</cuarta>
<quinta>26.1452093023256</quinta>
<sexta>34.0722142503711</sexta>
<septima></septima>
<octava></octava>
<Puertas>2</Puertas>
<Cilindros>3</Cilindros>
<vMAX>195</vMAX>
<aceleracion>9.8</aceleracion>
<Cons1>4.6</Cons1>
<Cons2>5.3</Cons2>
<Cons3>6.6</Cons3>
<EmisionesCo2>122.96</EmisionesCo2>
<anioComienzo>2003</anioComienzo>
<anioFin>2006</anioFin>
</AZ>
<AZ>
<Motorizacion>0.7 61cv / 45kw</Motorizacion>
<kw>45.4877</kw>
<combustible>G</combustible>
<cv>61</cv>
<cilindrada>698</cilindrada>
<pesoVacio>740</pesoVacio>
<Par>95</Par>
<marchas>6</marchas>
<cambio>M</cambio>
<segunda>11.4718775510204</segunda>
<tercera>14.9500531914894</tercera>
<cuarta>18.9514091096739</cuarta>
<quinta>26.1452093023256</quinta>
<sexta>34.0722142503711</sexta>
<septima></septima>
<octava></octava>
<Puertas>2</Puertas>
<Cilindros>3</Cilindros>
<vMAX>150</vMAX>
<aceleracion>15.5</aceleracion>
<Cons1>4.1</Cons1>
<Cons2>4.9</Cons2>
<Cons3>6.2</Cons3>
<EmisionesCo2>113.68</EmisionesCo2>
<anioComienzo>2003</anioComienzo>
<anioFin>2006</anioFin>
</AZ>
<AZ>
<Motorizacion>0.7 61cv / 45kw Aut.</Motorizacion>
<kw>45.4877</kw>
<combustible>G</combustible>
<cv>61</cv>
<cilindrada>698</cilindrada>
<pesoVacio>740</pesoVacio>
<Par>95</Par>
<marchas>6</marchas>
<cambio>A</cambio>
<segunda>11.4718775510204</segunda>
<tercera>14.9500531914894</tercera>
<cuarta>18.9514091096739</cuarta>
<quinta>26.1452093023256</quinta>
<sexta>34.0722142503711</sexta>
<septima></septima>
<octava></octava>
<Puertas>2</Puertas>
<Cilindros>3</Cilindros>
<vMAX>150</vMAX>
<aceleracion>15.5</aceleracion>
<Cons1>4.1</Cons1>
<Cons2>4.9</Cons2>
<Cons3>6.2</Cons3>
<EmisionesCo2>113.68</EmisionesCo2>
<anioComienzo>2003</anioComienzo>
<anioFin>2006</anioFin>
</AZ>
<AZ>
<Motorizacion>0.7 82cv / 61kw</Motorizacion>
<kw>61.1474</kw>
<combustible>G</combustible>
<cv>82</cv>
<cilindrada>698</cilindrada>
<pesoVacio>740</pesoVacio>
<Par>110</Par>
<marchas>6</marchas>
<cambio>M</cambio>
<segunda>11.4718775510204</segunda>
<tercera>14.9500531914894</tercera>
<cuarta>18.9514091096739</cuarta>
<quinta>26.1452093023256</quinta>
<sexta>34.0722142503711</sexta>
<septima></septima>
<octava></octava>
<Puertas>2</Puertas>
<Cilindros>3</Cilindros>
<vMAX>175</vMAX>
<aceleracion>10.9</aceleracion>
<Cons1>4.3</Cons1>
<Cons2>5.1</Cons2>
<Cons3>6.3</Cons3>
<EmisionesCo2>118.32</EmisionesCo2>
<anioComienzo>2003</anioComienzo>
<anioFin>2006</anioFin>
</AZ>
<AZ>
<Motorizacion>0.7 82cv / 61kw Aut.</Motorizacion>
<kw>61.1474</kw>
<combustible>G</combustible>
<cv>82</cv>
<cilindrada>698</cilindrada>
<pesoVacio>740</pesoVacio>
<Par>110</Par>
<marchas>6</marchas>
<cambio>A</cambio>
<segunda>11.4718775510204</segunda>
<tercera>14.9500531914894</tercera>
<cuarta>18.9514091096739</cuarta>
<quinta>26.1452093023256</quinta>
<sexta>34.0722142503711</sexta>
<septima></septima>
<octava></octava>
<Puertas>2</Puertas>
<Cilindros>3</Cilindros>
<vMAX>175</vMAX>
<aceleracion>10.9</aceleracion>
<Cons1>4.3</Cons1>
<Cons2>5.1</Cons2>
<Cons3>6.3</Cons3>
<EmisionesCo2>118.32</EmisionesCo2>
<anioComienzo>2003</anioComienzo>
<anioFin>2006</anioFin>
</AZ>
</AA></modelo>
</marca>
</fichero>
